periodic_element_properties/__init__.py
periodic_element_properties/elements.py
periodic_element_properties/properties_of_elements.json
periodic_element_properties-0.2.1.dist-info/METADATA
periodic_element_properties-0.2.1.dist-info/WHEEL
periodic_element_properties-0.2.1.dist-info/RECORD
