Metadata-Version: 2.1
Name: periodic-element-properties
Version: 0.2.1
Summary: This package contains information about periodic elements and their properties
Author: Prithivee7
Author-email: getprithivee@gmail.com
Requires-Python: >=3.7,<4.0
Classifier: Programming Language :: Python :: 3
Classifier: Programming Language :: Python :: 3.7
Classifier: Programming Language :: Python :: 3.8
Classifier: Programming Language :: Python :: 3.9
Classifier: Programming Language :: Python :: 3.10
Classifier: Programming Language :: Python :: 3.11
